README.md
setup.py
timeunit/__init__.py
timeunit.egg-info/PKG-INFO
timeunit.egg-info/SOURCES.txt
timeunit.egg-info/dependency_links.txt
timeunit.egg-info/entry_points.txt
timeunit.egg-info/not-zip-safe
timeunit.egg-info/top_level.txt