Metadata-Version: 1.0
Name: timeunit
Version: 1.1.0
Summary: timeunit
Home-page: https://github.com/Ralph-Wang/timeunit-python
Author: Ralph-Wang
Author-email: ralph.wang1024@gmail.com
License: MIT
Keywords: timeunit
Platform: UNKNOWN
